TritonFactory/__init__.py
TritonFactory/Activations/__init__.py
TritonFactory/Activations/gelu.py
TritonFactory/Activations/leaky_relu.py
TritonFactory/Activations/relu.py
TritonFactory/Activations/silu.py
TritonFactory/Activations/softmax.py
TritonFactory/Layers/__init__.py
TritonFactory/Layers/linear.py
TritonFactory/Normalization/__init__.py
TritonFactory/Normalization/layernorm.py
TritonFactory/Normalization/rmsnorm.py
TritonFactory-1.0.1.dist-info/LICENSE
TritonFactory-1.0.1.dist-info/METADATA
TritonFactory-1.0.1.dist-info/WHEEL
TritonFactory-1.0.1.dist-info/top_level.txt
TritonFactory-1.0.1.dist-info/RECORD
